gearbest_api/__init__.py
gearbest_api-0.0.4.dist-info/LICENSE.md
gearbest_api-0.0.4.dist-info/METADATA
gearbest_api-0.0.4.dist-info/WHEEL
gearbest_api-0.0.4.dist-info/top_level.txt
gearbest_api-0.0.4.dist-info/RECORD
